docs/__init__.py
docs/conf.py
docs/example_google_docstring.py
notebooks/__init__.py
tests/__init__.py
tests/test_database.py
tests/test_environment.py
tests/test_model.py
youchoose/__init__.py
youchoose/data/__init__.py
youchoose/data/data_loading.py
youchoose/data/data_processing.py
youchoose/data/example_datasets/__init__.py
youchoose/data/example_datasets/instacart_dataset.py
youchoose/data/example_datasets/test_example_datasets.py
youchoose/data/ingestion/__init__.py
youchoose/data/ingestion/csv.py
youchoose/data/ingestion/graph.py
youchoose/data/ingestion/helper_functions.py
youchoose/data/ingestion/image.py
youchoose/data/ingestion/nosql.py
youchoose/data/ingestion/sql.py
youchoose/data/ingestion/text.py
youchoose/data/ingestion/video.py
youchoose/data/processing/__init__.py
youchoose/data_gen/__init__.py
youchoose/data_gen/create_adjancency_matrix.py
youchoose/data_gen/database_connection.py
youchoose/data_gen/download_instacart_data.py
youchoose/data_gen/make_dataset.py
youchoose/evaluate/__init__.py
youchoose/evaluate/auc.py
youchoose/extraction/__init__.py
youchoose/extraction/nn_latent_matrix_factorization.py
youchoose/interaction/__init__.py
youchoose/interaction/pairwise.py
youchoose/interaction/pointwise.py
youchoose/recommender/__init__.py
youchoose/recommender/deploy.py
youchoose/recommender/recommender.py
youchoose/utils/__init__.py
youchoose/utils/logging.py
youchoose/utils/sample.py
youchoose/visualization/__init__.py
youchoose/visualization/visualize.py
youchoose-0.1.2.dist-info/LICENSE
youchoose-0.1.2.dist-info/METADATA
youchoose-0.1.2.dist-info/WHEEL
youchoose-0.1.2.dist-info/top_level.txt
youchoose-0.1.2.dist-info/RECORD
